LATTE/.DS_Store
LATTE/LATTE_DV.py
LATTE/LATTEbrew.py
LATTE/LATTEutils.py
LATTE/__init__.py
LATTE/__main__.py
LATTE/_config.txt
LATTE/filters.py
LATTE/norm.py
LATTE/pyaneti_LATTE.py
LATTE/volunteers_for_method_paper
LATTE/LATTE_eep_data/eep_phase0.csv
LATTE/LATTE_eep_data/eep_phase2.csv
LATTE/LATTE_imgs/.DS_Store
LATTE/LATTE_imgs/LATTE_logo.jpeg
LATTE/LATTE_imgs/LATTE_logo.jpg
LATTE/LATTE_imgs/LATTE_logo.pdf
LATTE/LATTE_imgs/LATTE_logo.png
LATTE/LATTE_imgs/LATTE_logo_old.jpg
LATTE/LATTE_imgs/LATTE_logo_small.png
LATTE/LATTE_imgs/PHT_logo.jpg
LATTE/LATTE_imgs/TESS_logo.png
LATTE/__pycache__/LATTE_DV.cpython-37.pyc
LATTE/__pycache__/LATTEbrew.cpython-35.pyc
LATTE/__pycache__/LATTEbrew.cpython-37 2.pyc
LATTE/__pycache__/LATTEbrew.cpython-37.pyc
LATTE/__pycache__/LATTEutils.cpython-35.pyc
LATTE/__pycache__/LATTEutils.cpython-37 2.pyc
LATTE/__pycache__/LATTEutils.cpython-37.pyc
LATTE/__pycache__/__init__.cpython-35.pyc
LATTE/__pycache__/__init__.cpython-37.pyc
LATTE/__pycache__/__main__.cpython-35.pyc
LATTE/__pycache__/__main__.cpython-37.pyc
LATTE/__pycache__/filters.cpython-37 2.pyc
LATTE/__pycache__/filters.cpython-37.pyc
LATTE/__pycache__/norm.cpython-37 2.pyc
LATTE/__pycache__/norm.cpython-37.pyc
LATTE/pyaneti_LATTE/__init__.py
LATTE/test_output/.DS_Store
LATTE/test_output/55525572/.DS_Store
LATTE/test_output/55525572/55525572_aperture_size.png
LATTE/test_output/55525572/55525572_apertures_0.png
LATTE/test_output/55525572/55525572_background.png
LATTE/test_output/55525572/55525572_bls_first.png
LATTE/test_output/55525572/55525572_bls_second.png
LATTE/test_output/55525572/55525572_centroids.png
LATTE/test_output/55525572/55525572_data.txt
LATTE/test_output/55525572/55525572_data_pyaneti.dat
LATTE/test_output/55525572/55525572_eep.png
LATTE/test_output/55525572/55525572_fit_test.png
LATTE/test_output/55525572/55525572_flux_comparison.png
LATTE/test_output/55525572/55525572_fullLC_md.png
LATTE/test_output/55525572/55525572_individual_pixel_LCs_0.png
tessLATTE-1.0.21.dist-info/LICENSE
tessLATTE-1.0.21.dist-info/METADATA
tessLATTE-1.0.21.dist-info/WHEEL
tessLATTE-1.0.21.dist-info/entry_points.txt
tessLATTE-1.0.21.dist-info/top_level.txt
tessLATTE-1.0.21.dist-info/RECORD
