Metadata-Version: 2.1
Name: tessLATTE
Version: 1.0.21
Summary: Lightcurve Analysis Tool for Transiting Exoplanets
Home-page: https://github.com/noraeisner/LATTE
Author: Nora L. Eisner
Author-email: nora.eisner@new.ox.ac.uk
License: GNU Lesser General Public License v3.0
Platform: UNKNOWN
Classifier: License :: OSI Approved :: MIT License
Classifier: Programming Language :: Python :: 3
Classifier: Programming Language :: Python :: 3.7
Requires-Dist: numpy
Requires-Dist: pandas
Requires-Dist: seaborn
Requires-Dist: requests
Requires-Dist: lightkurve (>1.2.0)
Requires-Dist: matplotlib (==3.2.0)
Requires-Dist: astroplan
Requires-Dist: astroquery
Requires-Dist: sklearn
Requires-Dist: scipy
Requires-Dist: tess-point
Requires-Dist: reproject (>0.7)
Requires-Dist: reportlab
Requires-Dist: astropy (<=4.0)
Requires-Dist: mock (>2.0.0)
